fibe/__init__.py
fibe/core/classes.py
fibe/core/math.py
fibe/scripts/create_from_f_p_boundary.py
fibe/scripts/regrid_eqdsk.py
fibe/utils/boundary.py
fibe/utils/eqdsk.py
fibe/utils/plotting.py
fibe/utils/profiles.py
fibe-0.3.2.dist-info/licenses/LICENSE
fibe-0.3.2.dist-info/METADATA
fibe-0.3.2.dist-info/WHEEL
fibe-0.3.2.dist-info/entry_points.txt
fibe-0.3.2.dist-info/top_level.txt
fibe-0.3.2.dist-info/RECORD
